ec_tools_cli/__init__.py
ec_tools_cli/auto_run/__init__.py
ec_tools_cli/auto_run/cli.py
ec_tools_cli/auto_run/runner/__init__.py
ec_tools_cli/auto_run/runner/auto_runner.py
ec_tools_cli/auto_run/runner/cpp_runner.py
ec_tools_cli/auto_run/runner/py_runner.py
ec_tools_cli/backup_machine/__init__.py
ec_tools_cli/backup_machine/backup_machine.py
ec_tools_cli/backup_machine/cli.py
ec_tools_cli/backup_machine/unload_machine.py
ec_tools_cli/backup_machine/utils.py
ec_tools_cli/backup_machine/zip_storage.py
ec_tools_cli/backup_machine/data/config.py
ec_tools_cli/backup_machine/data/record.py
ec_tools_cli/common/__init__.py
ec_tools_cli/common/utils/__init__.py
ec_tools_cli/common/utils/logger_utils.py
ec_tools_cli/db/__init__.py
ec_tools_cli/db/cli.py
ec_tools_cli/enc/__init__.py
ec_tools_cli/enc/cli.py
ec_tools_cli/one_off/__init__.py
ec_tools_cli/one_off/migrate_db.py
ec_tools_cli/vault/__init__.py
ec_tools_cli/vault/cli.py
ec_tools_cli/vault/encryption.py
ec_tools_cli/vault/parameter/__init__.py
ec_tools_cli/vault/parameter/args.py
ec_tools_cli/vault/parameter/parameter.py
ec_tools_cli/vault/parameter/process.py
ec_tools_cli-0.1.1.dist-info/METADATA
ec_tools_cli-0.1.1.dist-info/WHEEL
ec_tools_cli-0.1.1.dist-info/entry_points.txt
ec_tools_cli-0.1.1.dist-info/top_level.txt
ec_tools_cli-0.1.1.dist-info/RECORD
